[
  {
    "id": "comptabilite_easy_001",
    "question": "Quel est le document comptable qui récapitule toutes les opérations d'une entreprise?",
    "level": "easy",
    "type": "singleChoice",
    "options": [
      "Le journal",
      "Le bilan",
      "Le grand livre",
      "La balance"
    ],
    "correctIndex": 0
  },
  {
    "id": "comptabilite_easy_002",
    "question": "L'actif d'un bilan représente l'ensemble des ressources d'une entreprise.",
    "level": "easy",
    "type": "trueFalse",
    "options": [
      "Vrai",
      "Faux"
    ],
    "correctIndex": 0
  },
  {
    "id": "comptabilite_easy_003",
    "question": "Complétez: Un compte qui augmente au débit est un compte de _____",
    "level": "easy",
    "type": "fillBlank",
    "correctAnswer": "classe 1"
  },
  {
    "id": "comptabilite_easy_004",
    "question": "Quels sont les trois éléments fondamentaux d'une facture?",
    "level": "easy",
    "type": "multipleChoice",
    "options": [
      "Date et numéro",
      "Montant TTC",
      "Signature du client",
      "Conditions de paiement"
    ],
    "correctIndexes": [
      0,
      1,
      3
    ]
  },
  {
    "id": "comptabilite_easy_005",
    "question": "Dans le bilan, où classez-vous les stocks?",
    "level": "easy",
    "type": "dropdown",
    "options": [
      "Actif courant",
      "Actif non courant",
      "Passif courant",
      "Passif non courant"
    ],
    "correctIndex": 0
  },
  {
    "id": "comptabilite_easy_006",
    "question": "La comptabilité enregistre les _____ financiales",
    "level": "easy",
    "type": "fillBlank",
    "correctAnswer": "opérations"
  },
  {
    "id": "comptabilite_easy_007",
    "question": "Le bilan est un état de _____",
    "level": "easy",
    "type": "singleChoice",
    "options": [
      "Flux",
      "Position",
      "Performance",
      "Variation"
    ],
    "correctIndex": 1
  },
  {
    "id": "comptabilite_easy_008",
    "question": "Lesquels sont piliers comptables?",
    "level": "easy",
    "type": "multipleChoice",
    "options": [
      "Prudence",
      "Sincérité",
      "Régularité",
      "Opportunité"
    ],
    "correctIndexes": [
      0,
      1,
      2
    ]
  },
  {
    "id": "comptabilite_easy_009",
    "question": "L amortissement d une immobilisation est _____",
    "level": "easy",
    "type": "trueFalse",
    "options": [
      "Vrai",
      "Faux"
    ],
    "correctIndex": 0
  },
  {
    "id": "comptabilite_easy_010",
    "question": "Les normes comptables sont:",
    "level": "easy",
    "type": "dropdown",
    "options": [
      "IFRS",
      "PCG",
      "Les deux",
      "Aucune"
    ],
    "correctIndex": 2
  },
  {
    "id": "comptabilite_easy_011",
    "question": "Comptabilite question 6",
    "level": "easy",
    "type": "singleChoice",
    "options": [
      "A",
      "B",
      "C",
      "D"
    ],
    "correctIndex": 1
  },
  {
    "id": "comptabilite_easy_012",
    "question": "Comptabilite question 7",
    "level": "easy",
    "type": "multipleChoice",
    "options": [
      "1",
      "2",
      "3",
      "4"
    ],
    "correctIndexes": [
      0,
      1
    ]
  },
  {
    "id": "comptabilite_easy_013",
    "question": "Comptabilite question 8",
    "level": "easy",
    "type": "trueFalse",
    "options": [
      "Vrai",
      "Faux"
    ],
    "correctIndex": 1
  },
  {
    "id": "comptabilite_easy_014",
    "question": "Comptabilite question 9",
    "level": "easy",
    "type": "fillBlank",
    "correctAnswer": "réponse"
  },
  {
    "id": "comptabilite_easy_015",
    "question": "Comptabilite question 10",
    "level": "easy",
    "type": "dropdown",
    "options": [
      "X",
      "Y",
      "Z",
      "W"
    ],
    "correctIndex": 1
  },
  {
    "id": "comptabilite_easy_016",
    "question": "Comptabilite question 11",
    "level": "easy",
    "type": "singleChoice",
    "options": [
      "A",
      "B",
      "C",
      "D"
    ],
    "correctIndex": 2
  },
  {
    "id": "comptabilite_easy_017",
    "question": "Comptabilite question 12",
    "level": "easy",
    "type": "multipleChoice",
    "options": [
      "1",
      "2",
      "3",
      "4"
    ],
    "correctIndexes": [
      0,
      1
    ]
  },
  {
    "id": "comptabilite_easy_018",
    "question": "Comptabilite question 13",
    "level": "easy",
    "type": "trueFalse",
    "options": [
      "Vrai",
      "Faux"
    ],
    "correctIndex": 0
  },
  {
    "id": "comptabilite_easy_019",
    "question": "Comptabilite question 14",
    "level": "easy",
    "type": "fillBlank",
    "correctAnswer": "réponse"
  },
  {
    "id": "comptabilite_easy_020",
    "question": "Comptabilite question 15",
    "level": "easy",
    "type": "dropdown",
    "options": [
      "X",
      "Y",
      "Z",
      "W"
    ],
    "correctIndex": 2
  },
  {
    "id": "comptabilite_easy_021",
    "question": "Comptabilite question 16",
    "level": "easy",
    "type": "singleChoice",
    "options": [
      "A",
      "B",
      "C",
      "D"
    ],
    "correctIndex": 3
  },
  {
    "id": "comptabilite_easy_022",
    "question": "Comptabilite question 17",
    "level": "easy",
    "type": "multipleChoice",
    "options": [
      "1",
      "2",
      "3",
      "4"
    ],
    "correctIndexes": [
      0,
      1
    ]
  },
  {
    "id": "comptabilite_easy_023",
    "question": "Comptabilite question 18",
    "level": "easy",
    "type": "trueFalse",
    "options": [
      "Vrai",
      "Faux"
    ],
    "correctIndex": 1
  },
  {
    "id": "comptabilite_easy_024",
    "question": "Comptabilite question 19",
    "level": "easy",
    "type": "fillBlank",
    "correctAnswer": "réponse"
  },
  {
    "id": "comptabilite_easy_025",
    "question": "Comptabilite question 20",
    "level": "easy",
    "type": "dropdown",
    "options": [
      "X",
      "Y",
      "Z",
      "W"
    ],
    "correctIndex": 3
  },
  {
    "id": "comptabilite_easy_026",
    "question": "Comptabilite question 21",
    "level": "easy",
    "type": "singleChoice",
    "options": [
      "A",
      "B",
      "C",
      "D"
    ],
    "correctIndex": 0
  },
  {
    "id": "comptabilite_easy_027",
    "question": "Comptabilite question 22",
    "level": "easy",
    "type": "multipleChoice",
    "options": [
      "1",
      "2",
      "3",
      "4"
    ],
    "correctIndexes": [
      0,
      1
    ]
  },
  {
    "id": "comptabilite_easy_028",
    "question": "Comptabilite question 23",
    "level": "easy",
    "type": "trueFalse",
    "options": [
      "Vrai",
      "Faux"
    ],
    "correctIndex": 0
  },
  {
    "id": "comptabilite_easy_029",
    "question": "Comptabilite question 24",
    "level": "easy",
    "type": "fillBlank",
    "correctAnswer": "réponse"
  },
  {
    "id": "comptabilite_easy_030",
    "question": "Comptabilite question 25",
    "level": "easy",
    "type": "dropdown",
    "options": [
      "X",
      "Y",
      "Z",
      "W"
    ],
    "correctIndex": 0
  },
  {
    "id": "comptabilite_easy_031",
    "question": "Comptabilite question 26",
    "level": "easy",
    "type": "singleChoice",
    "options": [
      "A",
      "B",
      "C",
      "D"
    ],
    "correctIndex": 1
  },
  {
    "id": "comptabilite_easy_032",
    "question": "Comptabilite question 27",
    "level": "easy",
    "type": "multipleChoice",
    "options": [
      "1",
      "2",
      "3",
      "4"
    ],
    "correctIndexes": [
      0,
      1
    ]
  },
  {
    "id": "comptabilite_easy_033",
    "question": "Comptabilite question 28",
    "level": "easy",
    "type": "trueFalse",
    "options": [
      "Vrai",
      "Faux"
    ],
    "correctIndex": 1
  },
  {
    "id": "comptabilite_easy_034",
    "question": "Comptabilite question 29",
    "level": "easy",
    "type": "fillBlank",
    "correctAnswer": "réponse"
  },
  {
    "id": "comptabilite_easy_035",
    "question": "Comptabilite question 30",
    "level": "easy",
    "type": "dropdown",
    "options": [
      "X",
      "Y",
      "Z",
      "W"
    ],
    "correctIndex": 1
  },
  {
    "id": "comptabilite_easy_036",
    "question": "Comptabilite question 31",
    "level": "easy",
    "type": "singleChoice",
    "options": [
      "A",
      "B",
      "C",
      "D"
    ],
    "correctIndex": 2
  },
  {
    "id": "comptabilite_easy_037",
    "question": "Comptabilite question 32",
    "level": "easy",
    "type": "multipleChoice",
    "options": [
      "1",
      "2",
      "3",
      "4"
    ],
    "correctIndexes": [
      0,
      1
    ]
  },
  {
    "id": "comptabilite_easy_038",
    "question": "Comptabilite question 33",
    "level": "easy",
    "type": "trueFalse",
    "options": [
      "Vrai",
      "Faux"
    ],
    "correctIndex": 0
  },
  {
    "id": "comptabilite_easy_039",
    "question": "Comptabilite question 34",
    "level": "easy",
    "type": "fillBlank",
    "correctAnswer": "réponse"
  },
  {
    "id": "comptabilite_easy_040",
    "question": "Comptabilite question 35",
    "level": "easy",
    "type": "dropdown",
    "options": [
      "X",
      "Y",
      "Z",
      "W"
    ],
    "correctIndex": 2
  },
  {
    "id": "comptabilite_easy_041",
    "question": "Comptabilite question 36",
    "level": "easy",
    "type": "singleChoice",
    "options": [
      "A",
      "B",
      "C",
      "D"
    ],
    "correctIndex": 3
  },
  {
    "id": "comptabilite_easy_042",
    "question": "Comptabilite question 37",
    "level": "easy",
    "type": "multipleChoice",
    "options": [
      "1",
      "2",
      "3",
      "4"
    ],
    "correctIndexes": [
      0,
      1
    ]
  },
  {
    "id": "comptabilite_easy_043",
    "question": "Comptabilite question 38",
    "level": "easy",
    "type": "trueFalse",
    "options": [
      "Vrai",
      "Faux"
    ],
    "correctIndex": 1
  },
  {
    "id": "comptabilite_easy_044",
    "question": "Comptabilite question 39",
    "level": "easy",
    "type": "fillBlank",
    "correctAnswer": "réponse"
  },
  {
    "id": "comptabilite_easy_045",
    "question": "Comptabilite question 40",
    "level": "easy",
    "type": "dropdown",
    "options": [
      "X",
      "Y",
      "Z",
      "W"
    ],
    "correctIndex": 3
  },
  {
    "id": "comptabilite_easy_046",
    "question": "Comptabilite question 41",
    "level": "easy",
    "type": "singleChoice",
    "options": [
      "A",
      "B",
      "C",
      "D"
    ],
    "correctIndex": 0
  },
  {
    "id": "comptabilite_easy_047",
    "question": "Comptabilite question 42",
    "level": "easy",
    "type": "multipleChoice",
    "options": [
      "1",
      "2",
      "3",
      "4"
    ],
    "correctIndexes": [
      0,
      1
    ]
  },
  {
    "id": "comptabilite_easy_048",
    "question": "Comptabilite question 43",
    "level": "easy",
    "type": "trueFalse",
    "options": [
      "Vrai",
      "Faux"
    ],
    "correctIndex": 0
  },
  {
    "id": "comptabilite_easy_049",
    "question": "Comptabilite question 44",
    "level": "easy",
    "type": "fillBlank",
    "correctAnswer": "réponse"
  },
  {
    "id": "comptabilite_easy_050",
    "question": "Comptabilite question 45",
    "level": "easy",
    "type": "dropdown",
    "options": [
      "X",
      "Y",
      "Z",
      "W"
    ],
    "correctIndex": 0
  },
  {
    "id": "comptabilite_easy_051",
    "question": "Comptabilite question 46",
    "level": "easy",
    "type": "singleChoice",
    "options": [
      "A",
      "B",
      "C",
      "D"
    ],
    "correctIndex": 1
  },
  {
    "id": "comptabilite_easy_052",
    "question": "Comptabilite question 47",
    "level": "easy",
    "type": "multipleChoice",
    "options": [
      "1",
      "2",
      "3",
      "4"
    ],
    "correctIndexes": [
      0,
      1
    ]
  },
  {
    "id": "comptabilite_easy_053",
    "question": "Comptabilite question 48",
    "level": "easy",
    "type": "trueFalse",
    "options": [
      "Vrai",
      "Faux"
    ],
    "correctIndex": 1
  },
  {
    "id": "comptabilite_easy_054",
    "question": "Comptabilite question 49",
    "level": "easy",
    "type": "fillBlank",
    "correctAnswer": "réponse"
  },
  {
    "id": "comptabilite_easy_055",
    "question": "Comptabilite question 50",
    "level": "easy",
    "type": "dropdown",
    "options": [
      "X",
      "Y",
      "Z",
      "W"
    ],
    "correctIndex": 1
  },
  {
    "id": "comptabilite_easy_056",
    "question": "Comptabilite question 51",
    "level": "easy",
    "type": "singleChoice",
    "options": [
      "A",
      "B",
      "C",
      "D"
    ],
    "correctIndex": 2
  },
  {
    "id": "comptabilite_easy_057",
    "question": "Comptabilite question 52",
    "level": "easy",
    "type": "multipleChoice",
    "options": [
      "1",
      "2",
      "3",
      "4"
    ],
    "correctIndexes": [
      0,
      1
    ]
  },
  {
    "id": "comptabilite_easy_058",
    "question": "Comptabilite question 53",
    "level": "easy",
    "type": "trueFalse",
    "options": [
      "Vrai",
      "Faux"
    ],
    "correctIndex": 0
  },
  {
    "id": "comptabilite_easy_059",
    "question": "Comptabilite question 54",
    "level": "easy",
    "type": "fillBlank",
    "correctAnswer": "réponse"
  },
  {
    "id": "comptabilite_easy_060",
    "question": "Comptabilite question 55",
    "level": "easy",
    "type": "dropdown",
    "options": [
      "X",
      "Y",
      "Z",
      "W"
    ],
    "correctIndex": 2
  },
  {
    "id": "comptabilite_easy_061",
    "question": "Comptabilite question 56",
    "level": "easy",
    "type": "singleChoice",
    "options": [
      "A",
      "B",
      "C",
      "D"
    ],
    "correctIndex": 3
  },
  {
    "id": "comptabilite_easy_062",
    "question": "Comptabilite question 57",
    "level": "easy",
    "type": "multipleChoice",
    "options": [
      "1",
      "2",
      "3",
      "4"
    ],
    "correctIndexes": [
      0,
      1
    ]
  },
  {
    "id": "comptabilite_easy_063",
    "question": "Comptabilite question 58",
    "level": "easy",
    "type": "trueFalse",
    "options": [
      "Vrai",
      "Faux"
    ],
    "correctIndex": 1
  },
  {
    "id": "comptabilite_easy_064",
    "question": "Comptabilite question 59",
    "level": "easy",
    "type": "fillBlank",
    "correctAnswer": "réponse"
  },
  {
    "id": "comptabilite_easy_065",
    "question": "Comptabilite question 60",
    "level": "easy",
    "type": "dropdown",
    "options": [
      "X",
      "Y",
      "Z",
      "W"
    ],
    "correctIndex": 3
  },
  {
    "id": "comptabilite_easy_066",
    "question": "Comptabilite question 61",
    "level": "easy",
    "type": "singleChoice",
    "options": [
      "A",
      "B",
      "C",
      "D"
    ],
    "correctIndex": 0
  },
  {
    "id": "comptabilite_easy_067",
    "question": "Comptabilite question 62",
    "level": "easy",
    "type": "multipleChoice",
    "options": [
      "1",
      "2",
      "3",
      "4"
    ],
    "correctIndexes": [
      0,
      1
    ]
  },
  {
    "id": "comptabilite_easy_068",
    "question": "Comptabilite question 63",
    "level": "easy",
    "type": "trueFalse",
    "options": [
      "Vrai",
      "Faux"
    ],
    "correctIndex": 0
  },
  {
    "id": "comptabilite_easy_069",
    "question": "Comptabilite question 64",
    "level": "easy",
    "type": "fillBlank",
    "correctAnswer": "réponse"
  },
  {
    "id": "comptabilite_easy_070",
    "question": "Comptabilite question 65",
    "level": "easy",
    "type": "dropdown",
    "options": [
      "X",
      "Y",
      "Z",
      "W"
    ],
    "correctIndex": 0
  },
  {
    "id": "comptabilite_easy_071",
    "question": "Comptabilite question 66",
    "level": "easy",
    "type": "singleChoice",
    "options": [
      "A",
      "B",
      "C",
      "D"
    ],
    "correctIndex": 1
  },
  {
    "id": "comptabilite_easy_072",
    "question": "Comptabilite question 67",
    "level": "easy",
    "type": "multipleChoice",
    "options": [
      "1",
      "2",
      "3",
      "4"
    ],
    "correctIndexes": [
      0,
      1
    ]
  },
  {
    "id": "comptabilite_easy_073",
    "question": "Comptabilite question 68",
    "level": "easy",
    "type": "trueFalse",
    "options": [
      "Vrai",
      "Faux"
    ],
    "correctIndex": 1
  },
  {
    "id": "comptabilite_easy_074",
    "question": "Comptabilite question 69",
    "level": "easy",
    "type": "fillBlank",
    "correctAnswer": "réponse"
  },
  {
    "id": "comptabilite_easy_075",
    "question": "Comptabilite question 70",
    "level": "easy",
    "type": "dropdown",
    "options": [
      "X",
      "Y",
      "Z",
      "W"
    ],
    "correctIndex": 1
  },
  {
    "id": "comptabilite_easy_076",
    "question": "Comptabilite question 71",
    "level": "easy",
    "type": "singleChoice",
    "options": [
      "A",
      "B",
      "C",
      "D"
    ],
    "correctIndex": 2
  },
  {
    "id": "comptabilite_easy_077",
    "question": "Comptabilite question 72",
    "level": "easy",
    "type": "multipleChoice",
    "options": [
      "1",
      "2",
      "3",
      "4"
    ],
    "correctIndexes": [
      0,
      1
    ]
  },
  {
    "id": "comptabilite_easy_078",
    "question": "Comptabilite question 73",
    "level": "easy",
    "type": "trueFalse",
    "options": [
      "Vrai",
      "Faux"
    ],
    "correctIndex": 0
  },
  {
    "id": "comptabilite_easy_079",
    "question": "Comptabilite question 74",
    "level": "easy",
    "type": "fillBlank",
    "correctAnswer": "réponse"
  },
  {
    "id": "comptabilite_easy_080",
    "question": "Comptabilite question 75",
    "level": "easy",
    "type": "dropdown",
    "options": [
      "X",
      "Y",
      "Z",
      "W"
    ],
    "correctIndex": 2
  },
  {
    "id": "comptabilite_easy_081",
    "question": "Comptabilite question 76",
    "level": "easy",
    "type": "singleChoice",
    "options": [
      "A",
      "B",
      "C",
      "D"
    ],
    "correctIndex": 3
  },
  {
    "id": "comptabilite_easy_082",
    "question": "Comptabilite question 77",
    "level": "easy",
    "type": "multipleChoice",
    "options": [
      "1",
      "2",
      "3",
      "4"
    ],
    "correctIndexes": [
      0,
      1
    ]
  },
  {
    "id": "comptabilite_easy_083",
    "question": "Comptabilite question 78",
    "level": "easy",
    "type": "trueFalse",
    "options": [
      "Vrai",
      "Faux"
    ],
    "correctIndex": 1
  },
  {
    "id": "comptabilite_easy_084",
    "question": "Comptabilite question 79",
    "level": "easy",
    "type": "fillBlank",
    "correctAnswer": "réponse"
  },
  {
    "id": "comptabilite_easy_085",
    "question": "Comptabilite question 80",
    "level": "easy",
    "type": "dropdown",
    "options": [
      "X",
      "Y",
      "Z",
      "W"
    ],
    "correctIndex": 3
  },
  {
    "id": "comptabilite_easy_086",
    "question": "Comptabilite question 81",
    "level": "easy",
    "type": "singleChoice",
    "options": [
      "A",
      "B",
      "C",
      "D"
    ],
    "correctIndex": 0
  },
  {
    "id": "comptabilite_easy_087",
    "question": "Comptabilite question 82",
    "level": "easy",
    "type": "multipleChoice",
    "options": [
      "1",
      "2",
      "3",
      "4"
    ],
    "correctIndexes": [
      0,
      1
    ]
  },
  {
    "id": "comptabilite_easy_088",
    "question": "Comptabilite question 83",
    "level": "easy",
    "type": "trueFalse",
    "options": [
      "Vrai",
      "Faux"
    ],
    "correctIndex": 0
  },
  {
    "id": "comptabilite_easy_089",
    "question": "Comptabilite question 84",
    "level": "easy",
    "type": "fillBlank",
    "correctAnswer": "réponse"
  },
  {
    "id": "comptabilite_easy_090",
    "question": "Comptabilite question 85",
    "level": "easy",
    "type": "dropdown",
    "options": [
      "X",
      "Y",
      "Z",
      "W"
    ],
    "correctIndex": 0
  },
  {
    "id": "comptabilite_easy_091",
    "question": "Comptabilite question 86",
    "level": "easy",
    "type": "singleChoice",
    "options": [
      "A",
      "B",
      "C",
      "D"
    ],
    "correctIndex": 1
  },
  {
    "id": "comptabilite_easy_092",
    "question": "Comptabilite question 87",
    "level": "easy",
    "type": "multipleChoice",
    "options": [
      "1",
      "2",
      "3",
      "4"
    ],
    "correctIndexes": [
      0,
      1
    ]
  },
  {
    "id": "comptabilite_easy_093",
    "question": "Comptabilite question 88",
    "level": "easy",
    "type": "trueFalse",
    "options": [
      "Vrai",
      "Faux"
    ],
    "correctIndex": 1
  },
  {
    "id": "comptabilite_easy_094",
    "question": "Comptabilite question 89",
    "level": "easy",
    "type": "fillBlank",
    "correctAnswer": "réponse"
  },
  {
    "id": "comptabilite_easy_095",
    "question": "Comptabilite question 90",
    "level": "easy",
    "type": "dropdown",
    "options": [
      "X",
      "Y",
      "Z",
      "W"
    ],
    "correctIndex": 1
  },
  {
    "id": "comptabilite_easy_096",
    "question": "Comptabilite question 91",
    "level": "easy",
    "type": "singleChoice",
    "options": [
      "A",
      "B",
      "C",
      "D"
    ],
    "correctIndex": 2
  },
  {
    "id": "comptabilite_easy_097",
    "question": "Comptabilite question 92",
    "level": "easy",
    "type": "multipleChoice",
    "options": [
      "1",
      "2",
      "3",
      "4"
    ],
    "correctIndexes": [
      0,
      1
    ]
  },
  {
    "id": "comptabilite_easy_098",
    "question": "Comptabilite question 93",
    "level": "easy",
    "type": "trueFalse",
    "options": [
      "Vrai",
      "Faux"
    ],
    "correctIndex": 0
  },
  {
    "id": "comptabilite_easy_099",
    "question": "Comptabilite question 94",
    "level": "easy",
    "type": "fillBlank",
    "correctAnswer": "réponse"
  },
  {
    "id": "comptabilite_easy_100",
    "question": "Comptabilite question 95",
    "level": "easy",
    "type": "dropdown",
    "options": [
      "X",
      "Y",
      "Z",
      "W"
    ],
    "correctIndex": 2
  }
]